<?xml version="1.0"?>
<!--
  SPDX-License-Identifier: LGPL-2.1-or-later
  SPDX-FileCopyrightText: Copyright © the xdg-desktop-portal contributors
-->

<node name="/" xmlns:doc="http://www.freedesktop.org/dbus/1.0/doc.dtd">
  <!--
      org.freedesktop.portal.Vision:
      @short_description: Portal for local vision model tasks

      This documentation describes version 4 of this interface.
  -->
  <interface name="org.freedesktop.portal.Vision">
    <method name="GetUseCaseAvailability">
      <arg type="s" name="use_case" direction="in"/>
      <annotation name="org.qtproject.QtDBus.QtTypeName.In1" value="QVariantMap"/>
      <arg type="a{sv}" name="options" direction="in"/>
      <arg type="(bss)" name="availability" direction="out"/>
    </method>

    <!--
        CreateSession:
        @parent_window: Identifier for the application window, see :doc:`window-identifiers`
        @use_case: ``vision.describe`` for image descriptions,
          ``vision.ocr`` for text extraction, or ``vision.segment`` for object boxes
        @instructions: Stable system instructions for this session
        @options: Vardict with optional further information
        @handle: Object path for the :ref:`org.freedesktop.portal.Request` object representing this call

        The session @use_case selects which vision operation is permitted for
        the session. Create separate sessions for different vision tasks. The
        session handle is returned in the Request response under the
        ``session_handle`` key.
    -->
    <method name="CreateSession">
      <arg type="s" name="parent_window" direction="in"/>
      <arg type="s" name="use_case" direction="in"/>
      <arg type="s" name="instructions" direction="in"/>
      <annotation name="org.qtproject.QtDBus.QtTypeName.In3" value="QVariantMap"/>
      <arg type="a{sv}" name="options" direction="in"/>
      <arg type="o" name="handle" direction="out"/>
    </method>

    <method name="Prewarm">
      <arg type="o" name="session_handle" direction="in"/>
      <annotation name="org.qtproject.QtDBus.QtTypeName.In1" value="QVariantMap"/>
      <arg type="a{sv}" name="options" direction="in"/>
      <arg type="o" name="handle" direction="out"/>
    </method>

    <!--
        StreamDescribe:
        @session_handle: A ``vision.describe`` session handle returned by CreateSession
        @image: Base64-encoded PNG or JPEG image bytes; the encoded payload
          must fit within the session bus message limit
        @options: Vardict with optional further information
        Natural-language image description tokens are emitted as
        VisionTextReceived signals while this call is in progress.
    -->
    <method name="StreamDescribe">
      <arg type="o" name="session_handle" direction="in"/>
      <arg type="s" name="image" direction="in"/>
      <annotation name="org.qtproject.QtDBus.QtTypeName.In2" value="QVariantMap"/>
      <arg type="a{sv}" name="options" direction="in"/>
      <arg type="o" name="handle" direction="out"/>
    </method>

    <!--
        StreamOcr:
        @session_handle: A ``vision.ocr`` session handle returned by CreateSession
        @image: Base64-encoded PNG or JPEG image bytes; the encoded payload
          must fit within the session bus message limit
        @options: Vardict with optional further information
        Text extracted from the image is emitted as VisionTextReceived signals
        while this call is in progress.
    -->
    <method name="StreamOcr">
      <arg type="o" name="session_handle" direction="in"/>
      <arg type="s" name="image" direction="in"/>
      <annotation name="org.qtproject.QtDBus.QtTypeName.In2" value="QVariantMap"/>
      <arg type="a{sv}" name="options" direction="in"/>
      <arg type="o" name="handle" direction="out"/>
    </method>

    <!--
        StreamSegment:
        @session_handle: A ``vision.segment`` session handle returned by CreateSession
        @image: Base64-encoded PNG or JPEG image bytes; the encoded payload
          must fit within the session bus message limit
        @options: Vardict with optional further information
        Detected objects are emitted as VisionSegmentsReceived signals.

        Segment coordinates are normalized rectangles in the ``0.0..1.0``
        range relative to the image dimensions.
    -->
    <method name="StreamSegment">
      <arg type="o" name="session_handle" direction="in"/>
      <arg type="s" name="image" direction="in"/>
      <annotation name="org.qtproject.QtDBus.QtTypeName.In2" value="QVariantMap"/>
      <arg type="a{sv}" name="options" direction="in"/>
      <arg type="o" name="handle" direction="out"/>
    </method>

    <signal name="ModelLoading">
      <arg type="o" name="request_handle"/>
      <arg type="o" name="session_handle"/>
      <arg type="s" name="message"/>
    </signal>

    <signal name="VisionTextReceived">
      <arg type="o" name="request_handle"/>
      <arg type="o" name="session_handle"/>
      <arg type="s" name="text"/>
      <arg type="b" name="done"/>
    </signal>

    <signal name="VisionSegmentsReceived">
      <arg type="o" name="request_handle"/>
      <arg type="o" name="session_handle"/>
      <arg type="a(sddddd)" name="segments"/>
      <arg type="b" name="done"/>
    </signal>

    <property name="version" type="u" access="read"/>
  </interface>
</node>
